django_user_status/__init__.py
django_user_status/middleware.py
django_user_status/urls.py
django_user_status/templatetags/__init__.py
django_user_status/templatetags/user_status_tags.py
django_user_status/tests/__init__.py
django_user_status/tests/test_user_status.py
django_user_status-0.1.3.dist-info/licenses/LICENSE
django_user_status-0.1.3.dist-info/METADATA
django_user_status-0.1.3.dist-info/WHEEL
django_user_status-0.1.3.dist-info/top_level.txt
django_user_status-0.1.3.dist-info/RECORD
