Metadata-Version: 2.4
Name: django-user-status
Version: 0.1.3
Summary: A Django package to show online/offline status and last seen time.
Author-email: Hossein Tajfirouz <hosseintajfirouz@gmail.com>
Project-URL: Homepage, https://github.com/ht21992/django-user-status
Project-URL: Issues, https://github.com/ht21992/django-user-status/issues
Classifier: Programming Language :: Python :: 3
Classifier: License :: OSI Approved :: MIT License
Classifier: Operating System :: OS Independent
Classifier: Framework :: Django
Classifier: Framework :: Django :: 4.0
Requires-Python: >=3.8
License-File: LICENSE
Requires-Dist: Django>=4.0
Dynamic: license-file
